BayesBrain/DesignMaker.py
BayesBrain/__init__.py
BayesBrain/datasim.py
BayesBrain/glm.py
BayesBrain/models.py
BayesBrain/scratch.py
BayesBrain/utils.py
bayesbrain-0.1.1.dist-info/licenses/LICENSE
bayesbrain-0.1.1.dist-info/METADATA
bayesbrain-0.1.1.dist-info/WHEEL
bayesbrain-0.1.1.dist-info/top_level.txt
bayesbrain-0.1.1.dist-info/RECORD
